.DS_Store
cabana/__init__.py
cabana/__main__.py
cabana/analyzer.py
cabana/batch.py
cabana/batch_processor.py
cabana/cabana-gui.py
cabana/cabana.py
cabana/cabana_gui.py
cabana/constants.py
cabana/convcrf.py
cabana/correct.py
cabana/detector.py
cabana/hdm.py
cabana/log.py
cabana/models.py
cabana/orientation.py
cabana/segmenter.py
cabana/ui.py
cabana/utils.py
cabana/version_info.py
cabana-0.0.2.dist-info/LICENSE
cabana-0.0.2.dist-info/METADATA
cabana-0.0.2.dist-info/WHEEL
cabana-0.0.2.dist-info/entry_points.txt
cabana-0.0.2.dist-info/top_level.txt
cabana-0.0.2.dist-info/RECORD
