Metadata-Version: 2.2
Name: cabana
Version: 0.0.2
Summary: Collagen fibre analyser for quantifying collagen fibre architecture in IHC and fluorescence microscopy images.
Home-page: https://github.com/lxfhfut/cabana.git
Author: Gavin Lin
Author-email: x.lin@garvan.org.au
Classifier: Programming Language :: Python :: 3
Classifier: License :: OSI Approved :: MIT License
Classifier: Operating System :: OS Independent
License-File: LICENSE
Requires-Dist: colorlog
Requires-Dist: gitpython
Requires-Dist: imutils
Requires-Dist: jaraco.collections
Requires-Dist: numba
Requires-Dist: opencv-python
Requires-Dist: pip-chill
Requires-Dist: pyqt5
Requires-Dist: pyyaml
Requires-Dist: scikit-learn
Requires-Dist: seaborn
Requires-Dist: seaborn-image
Requires-Dist: send2trash
Requires-Dist: tomli
Requires-Dist: torch
Requires-Dist: tqdm
Requires-Dist: twine
Dynamic: author
Dynamic: author-email
Dynamic: classifier
Dynamic: description
Dynamic: description-content-type
Dynamic: home-page
Dynamic: requires-dist
Dynamic: summary
